daison.cpython-312-darwin.so
daison-0.4.dist-info/RECORD
daison-0.4.dist-info/LICENSE
daison-0.4.dist-info/WHEEL
daison-0.4.dist-info/top_level.txt
daison-0.4.dist-info/METADATA
