Metadata-Version: 2.1
Name: daison
Version: 0.4
Summary: An interface to Daison databases from Python
Home-page: UNKNOWN
Author: Krasimir Angelov
Author-email: kr.angelov@gmail.com
License: BSD
Platform: UNKNOWN
License-File: LICENSE
